dark_keeper/__init__.py
dark_keeper/base.py
dark_keeper/exceptions.py
dark_keeper/exports.py
dark_keeper/handlers.py
dark_keeper/http.py
dark_keeper/mongo.py
dark_keeper/parsers.py
dark_keeper/storages.py
dark_keeper-0.3.1.dist-info/LICENSE
dark_keeper-0.3.1.dist-info/METADATA
dark_keeper-0.3.1.dist-info/WHEEL
dark_keeper-0.3.1.dist-info/top_level.txt
dark_keeper-0.3.1.dist-info/RECORD
