Metadata-Version: 2.1
Name: dark-keeper
Version: 0.3.1
Summary: Dark Keeper is open source simple web-parser for podcast-sites
Home-page: https://github.com/itcrab/dark-keeper
Author: Arcady Usov
Author-email: itcrab@gmail.com
Maintainer: Arcady Usov
Maintainer-email: itcrab@gmail.com
License: MIT License
Platform: UNKNOWN
Classifier: Programming Language :: Python
Classifier: Programming Language :: Python :: 3.6
Classifier: Programming Language :: Python :: 3.7
Classifier: Programming Language :: Python :: 3.8
Classifier: Programming Language :: Python :: Implementation :: CPython
Classifier: License :: OSI Approved :: MIT License
Classifier: Development Status :: 5 - Production/Stable
Classifier: Environment :: Console
Classifier: Intended Audience :: Developers
Classifier: Operating System :: OS Independent
Classifier: Topic :: Software Development :: Libraries :: Application Frameworks
Classifier: Topic :: Software Development :: Libraries :: Python Modules
Classifier: Topic :: Internet :: WWW/HTTP
Requires-Dist: cssselect (==1.1.0)
Requires-Dist: lxml (==4.6.2)
Requires-Dist: pymongo (==3.11.3)
Requires-Dist: requests (==2.25.1)
